despeech/__init__.py
despeech/converter.py
tests/__init__.py
tests/test_converter.py
despeech-0.0.2.dist-info/LICENSE
despeech-0.0.2.dist-info/METADATA
despeech-0.0.2.dist-info/WHEEL
despeech-0.0.2.dist-info/top_level.txt
despeech-0.0.2.dist-info/RECORD
