Metadata-Version: 2.1
Name: despeech
Version: 0.0.2
Summary: Tool for converting direct speech in German into indirect one
Home-page: https://github.com/lnpetrova/despeech
Author: Lidiia Ostyakova
Author-email: lostaaa15@gmail.com
License: UNKNOWN
Platform: UNKNOWN
Classifier: Programming Language :: Python :: 3
Classifier: License :: OSI Approved :: MIT License
Classifier: Operating System :: OS Independent
Requires-Python: >=3.6
Requires-Dist: nltk
Requires-Dist: uralicNLP
